Decode/Decode24.v
module Decode24(out, in);
input[1:0] in;//2 bit input
output[3:0] out;//4 bit output

wire notA, notB;//2 wires

not not0(notA, in[0]);//calling not function with 2 paremeters
not not1(notB, in[1]);//calling not function with 2 paremeters
and and0(out[0], notA, notB);//calling and function with 3 paremeters
and and1(out[1], in[0], notB);//calling and function with 3 paremeters
and and2(out[2], in[1], notA);//calling and function with 3 paremeters
and and3(out[3], in[0], in[1]);//calling and function with 3 paremeters


endmodule

Decode/Decode24Test.v
`timescale 1ns / 1ps

////////////////////////////////////////////////////////////////////////////////
// Company: 
// Engineer:
//
// Create Date:   15:06:33 03/02/2009
// Design Name:   Decode24
// Module Name:   E:/350/Lab6/Decode24/Decode24Test.v
// Project Name:  Decode24
// Target Device:  
// Tool versions:  
// Description: 
//
// Verilog Test Fixture created by ISE for module: Decode24
//
// Dependencies:
// 
// Revision:
// Revision 0.01 - File Created
// Additional Comments:
// 
////////////////////////////////////////////////////////////////////////////////

`define STRLEN 15
module Decode24Test_v;
	initial //This initial block used to dump all wire/reg values to dump file
     begin
       $dumpfile("Decode24Test.vcd");
       $dumpvars(0, Decode24Test_v);
     end

	task passTest;
		input [3:0] actualOut, expectedOut;
		input [`STRLEN*8:0] testType;
		inout [7:0] passed;
	
		if(actualOut == expectedOut) begin $display ("%s passed", testType); passed = passed + 1; end
		else $display ("%s failed: %d should be %d", testType, actualOut, expectedOut);
	endtask
	
	task allPassed;
		input [7:0] passed;
		input [7:0] numTests;
		
		if(passed == numTests) $display ("All tests passed");
		else $display("Some tests failed");
	endtask
	
	// Inputs
	reg [1:0] in;
	reg [7:0] passed;

	// Outputs
	wire [3:0] out;

	// Instantiate the Unit Under Test (UUT)
	Decode24 uut (
		.in(in), 
		.out(out)
	);

	initial begin
		// Initialize Inputs
		in = 0;
		passed = 0;

		// Add stimulus here
		#90; in = 0; #10; passTest(out, 1, "Input 0", passed);
		#90; in = 1; #10; passTest(out, 2, "Input 1", passed);
		#90; in = 2; #10; passTest(out, 4, "Input 2", passed);
		#90; in = 3; #10; passTest(out, 8, "Input 3", passed);
		#90;
		
		allPassed(passed, 4);

	end
      
endmodule

Decode/Decode24Test.vcd
$date
	Thu Oct 19 21:50:13 2023
$end
$version
	Icarus Verilog
$end
$timescale
	1ps
$end
$scope module Decode24Test_v $end
$var wire 4 ! out [3:0] $end
$var reg 2 " in [1:0] $end
$var reg 8 # passed [7:0] $end
$scope module uut $end
$var wire 2 $ in [1:0] $end
$var wire 1 % notA $end
$var wire 1 & notB $end
$var wire 4 ' out [3:0] $end
$upscope $end
$scope task allPassed $end
$var reg 8 ( numTests [7:0] $end
$var reg 8 ) passed [7:0] $end
$upscope $end
$scope task passTest $end
$var reg 4 * actualOut [3:0] $end
$var reg 4 + expectedOut [3:0] $end
$var reg 8 , passed [7:0] $end
$var reg 121 - testType [120:0] $end
$upscope $end
$upscope $end
$enddefinitions $end
#0
$dumpvars
bx -
bx ,
bx +
bx *
bx )
bx (
b1 '
1&
1%
b0 $
b0 #
b0 "
b1 !
$end
#100000
b1 #
b1 ,
b1001001011011100111000001110101011101000010000000110000 -
b1 +
b1 *
#190000
0%
b10 !
b10 '
b1 "
b1 $
#200000
b10 #
b10 ,
b1001001011011100111000001110101011101000010000000110001 -
b10 +
b10 *
#290000
1%
0&
b100 !
b100 '
b10 "
b10 $
#300000
b11 #
b11 ,
b1001001011011100111000001110101011101000010000000110010 -
b100 +
b100 *
#390000
0%
b1000 !
b1000 '
b11 "
b11 $
#400000
b100 #
b100 ,
b1001001011011100111000001110101011101000010000000110011 -
b1000 +
b1000 *
#490000
b100 (
b100 )
